azureml/__init__.py
azureml/designer/__init__.py
azureml/designer/tools/__init__.py
azureml/designer/tools/model/__init__.py
azureml/designer/tools/model/azure_blob_helper.py
azureml/designer/tools/model/entry_function.py
azureml/designer/tools/model/http_request_helper.py
azureml/designer/tools/model/main.py
azureml/designer/tools/model/model_operation_processor.py
azureml/designer/tools/model/model_package_helper.py
azureml/designer/tools/model/package_info.py
azureml/designer/tools/model/retry.py
azureml/designer/tools/model/service_info_helper.py
azureml/designer/tools/model/service_operation_processor.py
azureml/designer/tools/model/smt_operation_helper.py
azureml/designer/tools/model/tool_constants.py
azureml/designer/tools/model/tool_exceptions.py
azureml/designer/tools/model/workspace_client.py
azureml_designer_model_tools-0.0.2.dist-info/METADATA
azureml_designer_model_tools-0.0.2.dist-info/WHEEL
azureml_designer_model_tools-0.0.2.dist-info/entry_points.txt
azureml_designer_model_tools-0.0.2.dist-info/top_level.txt
azureml_designer_model_tools-0.0.2.dist-info/RECORD
