Metadata-Version: 2.1
Name: azureml-designer-model-tools
Version: 0.0.2
Summary: UNKNOWN
Home-page: UNKNOWN
Author: Microsoft Crop
License: UNKNOWN
Platform: any
Classifier: Programming Language :: Python :: 3
Classifier: License :: Other/Proprietary License
Classifier: Operating System :: OS Independent
Requires-Python: >=3.6
Requires-Dist: azureml-designer-serving (>=0.0.6)
Requires-Dist: azure-storage-blob (==12.3.0)
